hotel_names/__init__.py
hotel_names/hotel_names.py
hotel_names-0.0.1.dist-info/LICENSE
hotel_names-0.0.1.dist-info/METADATA
hotel_names-0.0.1.dist-info/WHEEL
hotel_names-0.0.1.dist-info/entry_points.txt
hotel_names-0.0.1.dist-info/top_level.txt
hotel_names-0.0.1.dist-info/RECORD
