Metadata-Version: 2.1
Name: hotel-names
Version: 0.0.1
Summary: Generate random hotel names
Home-page: https://github.com/partojkander/hotel-names
Author: Pär Tojkander
Author-email: UNKNOWN
License: MIT
Platform: UNKNOWN
Classifier: Development Status :: 2 - Pre-Alpha
Classifier: Environment :: Console
Classifier: License :: OSI Approved :: MIT License
Classifier: Operating System :: OS Independent
Classifier: Programming Language :: Python
Classifier: Programming Language :: Python :: 3.8
